from_jupyter/__init__.py
from_jupyter/__main__.py
from_jupyter/code.py
from_jupyter/code_processors.py
from_jupyter/dataframe.css
from_jupyter/export.py
from_jupyter/gist_client.py
from_jupyter/utils.py
from_jupyter-0.3.0.dist-info/entry_points.txt
from_jupyter-0.3.0.dist-info/WHEEL
from_jupyter-0.3.0.dist-info/METADATA
from_jupyter-0.3.0.dist-info/RECORD
