Metadata-Version: 2.1
Name: from-jupyter
Version: 0.3.0
Summary: Blogging from Jupyter notebooks
Home-page: https://github.com/fferegrino/from-jupyter
License: MIT
Author: Antonio Feregrino
Author-email: antonio.feregrino@gmail.com
Requires-Python: >=3.8,<4.0
Classifier: License :: OSI Approved :: MIT License
Classifier: Programming Language :: Python :: 3
Classifier: Programming Language :: Python :: 3.10
Classifier: Programming Language :: Python :: 3.8
Classifier: Programming Language :: Python :: 3.9
Requires-Dist: Pygments (>=2.12.0,<3.0.0)
Requires-Dist: imgkit (>=1.2.2,<2.0.0)
Requires-Dist: jupytext (>=1.13.8,<2.0.0)
Requires-Dist: requests (>=2.27.1,<3.0.0)
Project-URL: Repository, https://github.com/fferegrino/from-jupyter
